model_archiver/__init__.py
model_archiver/arg_parser.py
model_archiver/model_archiver_error.py
model_archiver/model_packaging.py
model_archiver/model_packaging_utils.py
model_archiver/version.py
model_archiver/manifest_components/__init__.py
model_archiver/manifest_components/engine.py
model_archiver/manifest_components/manifest.py
model_archiver/manifest_components/model.py
model_archiver/manifest_components/publisher.py
model_archiver-1.0.3.dist-info/LICENSE
model_archiver-1.0.3.dist-info/METADATA
model_archiver-1.0.3.dist-info/WHEEL
model_archiver-1.0.3.dist-info/entry_points.txt
model_archiver-1.0.3.dist-info/top_level.txt
model_archiver-1.0.3.dist-info/RECORD
