Metadata-Version: 2.1
Name: model-archiver
Version: 1.0.3
Summary: Model Archiver is used for creating archives of trained neural net models that can be consumed by MXNet-Model-Server inference
Home-page: https://github.com/awslabs/mxnet-model-server/model-archiver/
Author: MXNet SDK team
Author-email: noreply@amazon.com
License: Apache License Version 2.0
Keywords: MXNet Model Archive Archiver MMS Server Serving Deep Learning Inference AI
Platform: UNKNOWN
Requires-Dist: future
Requires-Dist: enum-compat
Provides-Extra: mxnet
Requires-Dist: mxnet (==1.3.1) ; extra == 'mxnet'
Provides-Extra: mxnet-cu90mkl
Requires-Dist: mxnet-cu90mkl (==1.3.1) ; extra == 'mxnet-cu90mkl'
Provides-Extra: mxnet-cu92mkl
Requires-Dist: mxnet-cu92mkl (==1.3.1) ; extra == 'mxnet-cu92mkl'
Provides-Extra: mxnet-mkl
Requires-Dist: mxnet-mkl (==1.3.1) ; extra == 'mxnet-mkl'
Provides-Extra: onnx
Requires-Dist: onnx (==1.1.1) ; extra == 'onnx'
